{
    "Order": {
        "Client": "Client_1",
        "Code": "CP-0001",
        "CreatedDate": "27.05.2024",        
        "OrderStatus": "confirmed",
        "ShelfLife": "29.05.2024",
        "VAT": "13"
    },
    "Client": {
        "Login": "Client_1"
    },
    "Product": [
        {
            "Code": "N-0001",
            "Brand": "Nokia",
            "ProductQuantity": "1"
        },
        {
            "Code": "N-0002",
            "Brand": "Nokia",
            "ProductQuantity": "1"
        }
    ],
    "Warehouse": {
        "Name": "Central warehouse"
    },
    "PickUpPoint": {
        "Name": null
    }    
}